MultiProdigy/__init__.py
MultiProdigy/agents/__init__.py
MultiProdigy/agents/agent_base.py
MultiProdigy/agents/echo_agent.py
MultiProdigy/agents/memory_agent.py
MultiProdigy/agents/ollama_agent.py
MultiProdigy/agents/task_manager_agent.py
MultiProdigy/agents/user_agent.py
MultiProdigy/bus/__init__.py
MultiProdigy/bus/bus.py
MultiProdigy/bus/message_bus.py
MultiProdigy/config/__init__.py
MultiProdigy/config/config.py
MultiProdigy/logging/__init__.py
MultiProdigy/logging/logger.py
MultiProdigy/plugins/__init__.py
MultiProdigy/runtime/__init__.py
MultiProdigy/runtime/engine.py
MultiProdigy/runtime/registry.py
MultiProdigy/runtime/runtime.py
MultiProdigy/runtime/scheduler.py
MultiProdigy/schemas/__init__.py
MultiProdigy/schemas/agent_config.py
MultiProdigy/schemas/agent_interface.py
MultiProdigy/schemas/message.py
MultiProdigy/schemas/schemas.py
MultiProdigy/support/__init__.py
MultiProdigy/support/error.py
MultiProdigy/support/health.py
MultiProdigy/support/matrices.py
MultiProdigy/utils/__init__.py
multiprodigy-0.1.0.dist-info/LICENSE
multiprodigy-0.1.0.dist-info/METADATA
multiprodigy-0.1.0.dist-info/WHEEL
multiprodigy-0.1.0.dist-info/RECORD
