Metadata-Version: 2.3
Name: MultiProdigy
Version: 0.1.0
Summary: Modular, Pydantic-powered multi-agent AI framework
License: GPL-3.0-or-later
Author: Abhay-Cerberus
Requires-Python: >=3.9,<4.0
Classifier: License :: OSI Approved :: GNU General Public License v3 or later (GPLv3+)
Classifier: Programming Language :: Python :: 3
Classifier: Programming Language :: Python :: 3.9
Classifier: Programming Language :: Python :: 3.10
Classifier: Programming Language :: Python :: 3.11
Classifier: Programming Language :: Python :: 3.12
Classifier: Programming Language :: Python :: 3.13
Requires-Dist: fastapi (>=0.95.0)
Requires-Dist: prometheus-client (>=0.16.0)
Requires-Dist: pydantic (>=2.0)
Requires-Dist: pydantic-settings (>=2.9.1)
Requires-Dist: python-dotenv (>=1.0.0)
Requires-Dist: python-multipart (>=0.0.6)
Requires-Dist: pyyaml (>=6.0)
Requires-Dist: redis (>=4.5.0)
Requires-Dist: structlog (>=23.1.0)
Requires-Dist: uvicorn (>=0.21.0)
